seminar/__init__.py
seminar/apis/__init__.py
seminar/apis/hugo.py
seminar/apis/kaggle.py
seminar/apis/sendgrid.py
seminar/apis/youtube.py
seminar/cli.py
seminar/commands/__init__.py
seminar/commands/group.py
seminar/commands/markdown.py
seminar/commands/meeting.py
seminar/commands/notebook.py
seminar/commands/paper.py
seminar/models/__init__.py
seminar/models/group.py
seminar/models/helpers.py
seminar/models/meeting.py
seminar/templates/group/invoke.yml.j2
seminar/templates/kaggle/kaggle.json
seminar/templates/kaggle/kaggle.json.gpg
seminar/templates/kaggle/kernel-metadata.json.j2
seminar/templates/notebooks/data-pathing.py.j2
seminar/templates/notebooks/header.html.j2
seminar/templates/notebooks/nb-metadata.json.j2
seminar/templates/notebooks/to-post.md.j2
seminar/templates/summaryfile.md.j2
seminar/utils/__init__.py
seminar/utils/config.py
seminar/utils/editFM.py
seminar/utils/environment.py
seminar/utils/search.py
seminar/utils/sort.py
seminar/utils/ucfcal.py
seminar/utils/validators.py
seminar_toolkit-0.1.1.dist-info/entry_points.txt
seminar_toolkit-0.1.1.dist-info/WHEEL
seminar_toolkit-0.1.1.dist-info/METADATA
seminar_toolkit-0.1.1.dist-info/RECORD
