Metadata-Version: 2.1
Name: seminar-toolkit
Version: 0.1.1
Summary: Optimized to manage Jupyter Notebook driven courseware with SSGs.
Home-page: https://john.muchovej.com/projects/seminar/
Author: John Muchovej
Author-email: 5000729+jmuchovej@users.noreply.github.com
Requires-Python: >=3.7.1,<4.0.0
Classifier: Programming Language :: Python :: 3
Classifier: Programming Language :: Python :: 3.8
Classifier: Programming Language :: Python :: 3.9
Requires-Dist: Jinja2 (>=2.11.2,<3.0.0)
Requires-Dist: Pygments (>=2.7.3,<3.0.0)
Requires-Dist: click (>=7.1.2,<8.0.0)
Requires-Dist: docker (>=4.4.1,<5.0.0)
Requires-Dist: emoji (>=0.6.0,<0.7.0)
Requires-Dist: jupyter (>=1.0.0,<2.0.0)
Requires-Dist: kaggle (>=1.5.10,<2.0.0)
Requires-Dist: nbconvert (>=6.0.7,<7.0.0)
Requires-Dist: nbformat (>=5.0.8,<6.0.0)
Requires-Dist: nbgrader (>=0.6.1,<0.7.0)
Requires-Dist: numpy (>=1.19.5,<2.0.0)
Requires-Dist: pandas (>=1.2.0,<2.0.0)
Requires-Dist: pandoc (>=1.0.2,<2.0.0)
Requires-Dist: pydantic (>=1.7.3,<2.0.0)
Requires-Dist: requests (>=2.25.1,<3.0.0)
Requires-Dist: ruamel.yaml (>=0.16.12,<0.17.0)
Requires-Dist: termcolor (>=1.1.0,<2.0.0)
